{
    "Ar36": {
        "error": 0.0006591971923242986,
        "error_type": "SEM",
        "filter_outliers_dict": {
            "filter_outliers": false,
            "iterations": 1,
            "std_devs": 2,
            "use_iqr_filtering": false,
            "use_standard_deviation_filtering": false
        },
        "fit": "Linear",
        "fn": 150,
        "include_baseline_error": false,
        "n": 150,
        "outlier_excluded": [],
        "reviewed": true,
        "user_excluded": [],
        "value": 0.07161743350499912
    },
    "Ar37": {
        "error": 0.010389942721287562,
        "error_type": "SEM",
        "filter_outliers_dict": {
            "filter_outliers": true,
            "iterations": 1,
            "std_devs": 2
        },
        "fit": "Linear",
        "value": 0.041209472703135144
    },
    "Ar38": {
        "error": 0.013919991596697155,
        "error_type": "SEM",
        "filter_outliers_dict": {
            "filter_outliers": false,
            "iterations": 0,
            "std_devs": 0,
            "use_iqr_filtering": false,
            "use_standard_deviation_filtering": false
        },
        "fit": "Linear",
        "fn": 150,
        "include_baseline_error": false,
        "n": 150,
        "outlier_excluded": [],
        "reviewed": true,
        "user_excluded": [],
        "value": 1.80590377734603
    },
    "Ar39": {
        "error": 0.024174021221227058,
        "error_type": "SEM",
        "filter_outliers_dict": {
            "filter_outliers": false,
            "iterations": 0,
            "std_devs": 0,
            "use_iqr_filtering": false,
            "use_standard_deviation_filtering": false
        },
        "fit": "Linear",
        "fn": 150,
        "include_baseline_error": false,
        "n": 150,
        "outlier_excluded": [],
        "reviewed": true,
        "user_excluded": [],
        "value": 147.25080376132559
    },
    "Ar40": {
        "error": 0.11526749580946173,
        "error_type": "SEM",
        "filter_outliers_dict": {
            "filter_outliers": false,
            "iterations": 0,
            "std_devs": 0,
            "use_iqr_filtering": false,
            "use_standard_deviation_filtering": false
        },
        "fit": "Linear",
        "fn": 150,
        "include_baseline_error": false,
        "n": 150,
        "outlier_excluded": [],
        "reviewed": true,
        "user_excluded": [],
        "value": 2173.9153365652387
    }
}