{
    "Ar36": {
        "error": 0.0001778521387261017,
        "error_type": "",
        "fit": "previous",
        "references": [
            {
                "exclude": false,
                "record_id": "ba-01-A-17474"
            }
        ],
        "value": 0.005381375529723128
    },
    "Ar37": {
        "error": 0.010315925985153683,
        "error_type": "",
        "fit": "previous",
        "references": [
            {
                "exclude": false,
                "record_id": "ba-01-A-17474"
            }
        ],
        "value": -0.02217470948380163
    },
    "Ar38": {
        "error": 0.010498314467701718,
        "error_type": "",
        "fit": "previous",
        "references": [
            {
                "exclude": false,
                "record_id": "ba-01-A-17474"
            }
        ],
        "value": 0.01738617835012748
    },
    "Ar39": {
        "error": 0.008689073530347435,
        "error_type": "",
        "fit": "previous",
        "references": [
            {
                "exclude": false,
                "record_id": "ba-01-A-17474"
            }
        ],
        "value": 0.02075423693389106
    },
    "Ar40": {
        "error": 0.019258426710665057,
        "error_type": "",
        "fit": "previous",
        "references": [
            {
                "exclude": false,
                "record_id": "ba-01-A-17474"
            }
        ],
        "value": 1.6586332974289983
    }
}